Workbook

Sheet Sales Data
A1: Transaction ID | B1: Date | C1: Cashier | D1: Category | E1: Product | F1: Quantity Sold | G1: Unit Price | H1: Unit Cost | I1: Discunt Rate | J1: Sales Target | K1: Payment Method | L1: Gross Sales | M1: Discount Amount | N1: Net Sales | O1: Total Cost | P1: Gross Profit | Q1: Profit Margin | R1: Target Status | S1: Sales Commision
A2: T001 | B2: 46237 | C2: Angela | D2: Beverage | E2: Ice Coffee | F2: 12 | G2: 95 | H2: 48 | I2: 0.05 | J2: 1000 | K2: Cash | L2: =F2*G2 -> 1140 | M2: =L2*I2 -> 57 | N2: =L2-M2 -> 1083 | O2: =F2*H2 -> 576 | P2: =N2-O2 -> 507 | Q2: =P2/N2 -> 0.46814404 | R2: =IF(N2>=J2,"Target Met", "Below Target") -> Target Met | S2: =IF(R2="Target Met",P2*Settings!B1,0) -> 25.35
A3: T002 | B3: 46237 | C3: Brian | D3: Meal | E3: Chicken Rice Bowl | F3: 8 | G3: 145 | H3: 90 | I3: 0 | J3: 1100 | K3: GCash | L3: =F3*G3 -> 1160 | M3: =L3*I3 -> 0 | N3: =L3-M3 -> 1160 | O3: =F3*H3 -> 720 | P3: =N3-O3 -> 440 | Q3: =P3/N3 -> 0.37931034 | R3: =IF(N3>=J3,"Target Met", "Below Target") -> Target Met | S3: =IF(R3="Target Met",P3*Settings!B1,0) -> 22
A4: T003 | B4: 46238 | C4: Carla | D4: Snack | E4: Cheese Sandwich | F4: 10 | G4: 85 | H4: 45 | I4: 0.05 | J4: 800 | K4: Cash | L4: =F4*G4 -> 850 | M4: =L4*I4 -> 42.5 | N4: =L4-M4 -> 807.5 | O4: =F4*H4 -> 450 | P4: =N4-O4 -> 357.5 | Q4: =P4/N4 -> 0.44272446 | R4: =IF(N4>=J4,"Target Met", "Below Target") -> Target Met | S4: =IF(R4="Target Met",P4*Settings!B1,0) -> 17.875
A5: T004 | B5: 46238 | C5: Daniel | D5: Beverage | E5: Milk Tea | F5: 15 | G5: 110 | H5: 60 | I5: 0.1 | J5: 1500 | K5: GCash | L5: =F5*G5 -> 1650 | M5: =L5*I5 -> 165 | N5: =L5-M5 -> 1485 | O5: =F5*H5 -> 900 | P5: =N5-O5 -> 585 | Q5: =P5/N5 -> 0.39393939 | R5: =IF(N5>=J5,"Target Met", "Below Target") -> Below Target | S5: =IF(R5="Target Met",P5*Settings!B4,0) -> 0
A6: T005 | B6: 46239 | C6: Angela | D6: Dessert | E6: Chocolate Brownie | F6: 18 | G6: 65 | H6: 32 | I6: 0 | J6: 1000 | K6: Cash | L6: =F6*G6 -> 1170 | M6: =L6*I6 -> 0 | N6: =L6-M6 -> 1170 | O6: =F6*H6 -> 576 | P6: =N6-O6 -> 594 | Q6: =P6/N6 -> 0.50769231 | R6: =IF(N6>=J6,"Target Met", "Below Target") -> Target Met | S6: =IF(R6="Target Met",P6*Settings!B1,0) -> 29.7
A7: T006 | B7: 46239 | C7: Brian | D7: Meal | E7: Tuna Pasta | F7: 7 | G7: 160 | H7: 98 | I7: 0.05 | J7: 1100 | K7: Card | L7: =F7*G7 -> 1120 | M7: =L7*I7 -> 56 | N7: =L7-M7 -> 1064 | O7: =F7*H7 -> 686 | P7: =N7-O7 -> 378 | Q7: =P7/N7 -> 0.35526316 | R7: =IF(N7>=J7,"Target Met", "Below Target") -> Below Target | S7: =IF(R7="Target Met",P7*Settings!B1,0) -> 0
A8: T007 | B8: 46240 | C8: Carla | D8: Beverage | E8: Fruit Smoothie | F8: 11 | G8: 120 | H8: 70 | I8: 0.05 | J8: 1200 | K8: GCash | L8: =F8*G8 -> 1320 | M8: =L8*I8 -> 66 | N8: =L8-M8 -> 1254 | O8: =F8*H8 -> 770 | P8: =N8-O8 -> 484 | Q8: =P8/N8 -> 0.38596491 | R8: =IF(N8>=J8,"Target Met", "Below Target") -> Target Met | S8: =IF(R8="Target Met",P8*Settings!B1,0) -> 24.2
A9: T008 | B9: 46240 | C9: Daniel | D9: Snack | E9: Nachos | F9: 9 | G9: 100 | H9: 55 | I9: 0 | J9: 850 | K9: Cash | L9: =F9*G9 -> 900 | M9: =L9*I9 -> 0 | N9: =L9-M9 -> 900 | O9: =F9*H9 -> 495 | P9: =N9-O9 -> 405 | Q9: =P9/N9 -> 0.45 | R9: =IF(N9>=J9,"Target Met", "Below Target") -> Target Met | S9: =IF(R9="Target Met",P9*Settings!B1,0) -> 20.25
A10: T009 | B10: 46241 | C10: Angela | D10: Meal | E10: Beef burger | F10: 6 | G10: 180 | H10: 115 | I10: 0.1 | J10: 1000 | K10: Card | L10: =F10*G10 -> 1080 | M10: =L10*I10 -> 108 | N10: =L10-M10 -> 972 | O10: =F10*H10 -> 690 | P10: =N10-O10 -> 282 | Q10: =P10/N10 -> 0.29012346 | R10: =IF(N10>=J10,"Target Met", "Below Target") -> Below Target | S10: =IF(R10="Target Met",P10*Settings!B1,0) -> 0
A11: T010 | B11: 46241 | C11: Brian | D11: Dessert | E11: Blueberry Muffin | F11: 14 | G11: 75 | H11: 38 | I11: 0.05 | J11: 1000 | K11: Cash | L11: =F11*G11 -> 1050 | M11: =L11*I11 -> 52.5 | N11: =L11-M11 -> 997.5 | O11: =F11*H11 -> 532 | P11: =N11-O11 -> 465.5 | Q11: =P11/N11 -> 0.46666667 | R11: =IF(N11>=J11,"Target Met", "Below Target") -> Below Target | S11: =IF(R11="Target Met",P11*Settings!B1,0) -> 0
A12: T011 | B12: 46244 | C12: Carla | D12: Beverage | E12: Hot Chocolate | F12: 13 | G12: 90 | H12: 44 | I12: 0 | J12: 1100 | K12: GCash | L12: =F12*G12 -> 1170 | M12: =L12*I12 -> 0 | N12: =L12-M12 -> 1170 | O12: =F12*H12 -> 572 | P12: =N12-O12 -> 598 | Q12: =P12/N12 -> 0.51111111 | R12: =IF(N12>=J12,"Target Met", "Below Target") -> Target Met | S12: =IF(R12="Target Met",P12*Settings!B1,0) -> 29.9
A13: T012 | B13: 46244 | C13: Daniel | D13: Meal | E13: Grilled Chicken Warp | F13: 10 | G13: 150 | H13: 92 | I13: 0.05 | J13: 1400 | K13: Card | L13: =F13*G13 -> 1500 | M13: =L13*I13 -> 75 | N13: =L13-M13 -> 1425 | O13: =F13*H13 -> 920 | P13: =N13-O13 -> 505 | Q13: =P13/N13 -> 0.35438596 | R13: =IF(N13>=J13,"Target Met", "Below Target") -> Target Met | S13: =IF(R13="Target Met",P13*Settings!B1,0) -> 25.25
A14: T013 | B14: 46245 | C14: Angela | D14: Snack | E14: Fries | F14: 16 | G14: 70 | H14: 35 | I14: 0.1 | J14: 1000 | K14: Cash | L14: =F14*G14 -> 1120 | M14: =L14*I14 -> 112 | N14: =L14-M14 -> 1008 | O14: =F14*H14 -> 560 | P14: =N14-O14 -> 448 | Q14: =P14/N14 -> 0.44444444 | R14: =IF(N14>=J14,"Target Met", "Below Target") -> Target Met | S14: =IF(R14="Target Met",P14*Settings!B1,0) -> 22.4
A15: T014 | B15: 46245 | C15: Brian | D15: Beverage | E15: Lemon Ices Tea | F15: 20 | G15: 60 | H15: 25 | I15: 0 | J15: 1100 | K15: GCash | L15: =F15*G15 -> 1200 | M15: =L15*I15 -> 0 | N15: =L15-M15 -> 1200 | O15: =F15*H15 -> 500 | P15: =N15-O15 -> 700 | Q15: =P15/N15 -> 0.58333333 | R15: =IF(N15>=J15,"Target Met", "Below Target") -> Target Met | S15: =IF(R15="Target Met",P15*Settings!B1,0) -> 35
A16: T015 | B16: 46246 | C16: Carla | D16: Dessert | E16: Cheesecake Slice | F16: 8 | G16: 130 | H16: 75 | I16: 0.05 | J16: 1000 | K16: Card | L16: =F16*G16 -> 1040 | M16: =L16*I16 -> 52 | N16: =L16-M16 -> 988 | O16: =F16*H16 -> 600 | P16: =N16-O16 -> 388 | Q16: =P16/N16 -> 0.39271255 | R16: =IF(N16>=J16,"Target Met", "Below Target") -> Below Target | S16: =IF(R16="Target Met",P16*Settings!B1,0) -> 0
A17: T016 | B17: 46246 | C17: Daniel | D17: Meal | E17: Pork Sisig Meal | F17: 9 | G17: 170 | H17: 105 | I17: 0.1 | J17: 1400 | K17: Cash | L17: =F17*G17 -> 1530 | M17: =L17*I17 -> 153 | N17: =L17-M17 -> 1377 | O17: =F17*H17 -> 945 | P17: =N17-O17 -> 432 | Q17: =P17/N17 -> 0.31372549 | R17: =IF(N17>=J17,"Target Met", "Below Target") -> Below Target | S17: =IF(R17="Target Met",P17*Settings!B1,0) -> 0
A18: T017 | B18: 46247 | C18: Angela | D18: Beverage | E18: Spanish Latte | F18: 14 | G18: 125 | H18: 68 | I18: 0.05 | J18: 1600 | K18: GCash | L18: =F18*G18 -> 1750 | M18: =L18*I18 -> 87.5 | N18: =L18-M18 -> 1662.5 | O18: =F18*H18 -> 952 | P18: =N18-O18 -> 710.5 | Q18: =P18/N18 -> 0.42736842 | R18: =IF(N18>=J18,"Target Met", "Below Target") -> Target Met | S18: =IF(R18="Target Met",P18*Settings!B1,0) -> 35.525
A19: T018 | B19: 46247 | C19: Brian | D19: Snack | E19: Chiken Empanada | F19: 17 | G19: 55 | H19: 28 | I19: 0 | J19: 900 | K19: Cash | L19: =F19*G19 -> 935 | M19: =L19*I19 -> 0 | N19: =L19-M19 -> 935 | O19: =F19*H19 -> 476 | P19: =N19-O19 -> 459 | Q19: =P19/N19 -> 0.49090909 | R19: =IF(N19>=J19,"Target Met", "Below Target") -> Target Met | S19: =IF(R19="Target Met",P19*Settings!B1,0) -> 22.95
A20: T019 | B20: 46248 | C20: Carla | D20: Dessert | E20: Banana Bread | F20: 12 | G20: 80 | H20: 42 | I20: 0.1 | J20: 900 | K20: GCash | L20: =F20*G20 -> 960 | M20: =L20*I20 -> 96 | N20: =L20-M20 -> 864 | O20: =F20*H20 -> 504 | P20: =N20-O20 -> 360 | Q20: =P20/N20 -> 0.41666667 | R20: =IF(N20>=J20,"Target Met", "Below Target") -> Below Target | S20: =IF(R20="Target Met",P20*Settings!B1,0) -> 0
A21: T020 | B21: 46248 | C21: Daniel | D21: Meal | E21: Vegetable Pasta | F21: 11 | G21: 140 | H21: 82 | I21: 0.05 | J21: 1450 | K21: Card | L21: =F21*G21 -> 1540 | M21: =L21*I21 -> 77 | N21: =L21-M21 -> 1463 | O21: =F21*H21 -> 902 | P21: =N21-O21 -> 561 | Q21: =P21/N21 -> 0.38345865 | R21: =IF(N21>=J21,"Target Met", "Below Target") -> Target Met | S21: =IF(R21="Target Met",P21*Settings!B1,0) -> 28.05

Sheet Settings
A1: Commission Rate | B1: 0.05
A3: Computaion | B3: Explanation
A4: Gross Sales | B4: Quantity Sold * Unit Price
A5: Discount Amount | B5: Gross Sales * Discount Rate
A6: Net Sales | B6: Gross Sales - Discount Amount
A7: Total Cost | B7: Quantity Sold * Unit Cost
A8: Gross Profit | B8: Net Sales - Total Cost
A9: Profit Margin | B9: Gross Profit / Net Sales
A10: Target Status | B10: Determine Whether Net Sales Reached the Target
A11: Sales Commission | B11: Gives a Commission only when the Sales Target is Met
A13: Measurement | B13: Correct Result
A14: Gross Sales
A15: Discount Amount
A16: Net Sales
A17: Total Cost
A18: Gross Profit
A19: Profit Margin
A20: Target Status
A21: Sales Commission

Sheet Sales Summary
A1: Key Performance Indicator | B1: Formula
A2: Total Numbers of Transaction | B2: =COUNTA('Sales Data'!A2:A21) -> 20
A3: Total Gross Sales | B3: =SUM('Sales Data'!L2:L21) -> 24185
A4: Total Discount Amount | B4: =SUM('Sales Data'!M2:M21) -> 1199.5
A5: Total Net Sales | B5: =SUM('Sales Data'!N2:N21) -> 22985.5
A6: Total Cost | B6: =SUM('Sales Data'!O2:O21) -> 13326
A7: Total Gross Profit | B7: =SUM('Sales Data'!P2:P21) -> 9659.5
A8: Average Net Sales per Transaction | B8: =AVERAGE('Sales Data'!N2:N21) -> 1149.275
A9: Average Profit Margin | B9: =AVERAGE('Sales Data'!Q2:Q21) -> 0.42289722
A10: Highest Net Sales | B10: =MAX('Sales Data'!N2:N21) -> 1662.5
A11: Lowest Net Sales | B11: =MIN('Sales Data'!N2:N21) -> 807.5
A12: Transactions That Met Target | B12: =COUNTIF('Sales Data'!R2:R21,"Target Met") -> 13
A13: Transactions Below Target | B13: =COUNTIF('Sales Data'!R2:R21,"Below Target") -> 7
A14: Total Commission | B14: =SUM('Sales Data'!S2:S21) -> 338.45
A17: Product Category | B17: Total Net Sales | C17: Total Gross Profit | D17: Number Of Transactions
A18: Beverage | B18: =SUMIF('Sales Data'!D2:D21,'Sales Summary'!A18,'Sales Data'!N2:N21) -> 7854.5 | C18: =SUMIF('Sales Data'!D2:D21,'Sales Summary'!A18,'Sales Data'!P2:P21) -> 3584.5 | D18: =COUNTIF('Sales Data'!D2:D21,'Sales Summary'!A18) -> 6
A19: Meal | B19: =SUMIF('Sales Data'!D3:D22,'Sales Summary'!A19,'Sales Data'!N3:N22) -> 7461 | C19: =SUMIF('Sales Data'!D3:D22,'Sales Summary'!A19,'Sales Data'!P3:P22) -> 2598 | D19: =COUNTIF('Sales Data'!D3:D22,'Sales Summary'!A19) -> 6
A20: Snack | B20: =SUMIF('Sales Data'!D4:D23,'Sales Summary'!A20,'Sales Data'!N4:N23) -> 3650.5 | C20: =SUMIF('Sales Data'!D4:D23,'Sales Summary'!A20,'Sales Data'!P4:P23) -> 1669.5 | D20: =COUNTIF('Sales Data'!D4:D23,'Sales Summary'!A20) -> 4
A21: Dessert | B21: =SUMIF('Sales Data'!D5:D24,'Sales Summary'!A21,'Sales Data'!N5:N24) -> 4019.5 | C21: =SUMIF('Sales Data'!D5:D24,'Sales Summary'!A21,'Sales Data'!P5:P24) -> 1807.5 | D21: =COUNTIF('Sales Data'!D5:D24,'Sales Summary'!A21) -> 4
A24: Cashier | B24: Total Net Sales | C24: Total Gross Profit | D24: Number Of Transaction
A25: Angela | B25: =SUMIF('Sales Data'!C2:C21,'Sales Data'!C2,'Sales Data'!N2:N21) -> 5895.5 | C25: =SUMIF('Sales Data'!C2:C21,'Sales Data'!C2,'Sales Data'!P2:P21) -> 2541.5 | D25: =COUNTIF('Sales Data'!C2:C21,'Sales Summary'!A25) -> 5
A26: Brian | B26: =SUMIF('Sales Data'!C3:C22,'Sales Data'!C3,'Sales Data'!N3:N22) -> 5356.5 | C26: =SUMIF('Sales Data'!C3:C22,'Sales Data'!C3,'Sales Data'!P3:P22) -> 2442.5 | D26: =COUNTIF('Sales Data'!C3:C22,'Sales Summary'!A26) -> 5
A27: Carla | B27: =SUMIF('Sales Data'!C4:C23,'Sales Data'!C4,'Sales Data'!N4:N23) -> 5083.5 | C27: =SUMIF('Sales Data'!C4:C23,'Sales Data'!C4,'Sales Data'!P4:P23) -> 2187.5 | D27: =COUNTIF('Sales Data'!C4:C23,'Sales Summary'!A27) -> 5
A28: Daniel | B28: =SUMIF('Sales Data'!C5:C24,'Sales Data'!C5,'Sales Data'!N5:N24) -> 6650 | C28: =SUMIF('Sales Data'!C5:C24,'Sales Data'!C5,'Sales Data'!P5:P24) -> 2488 | D28: =COUNTIF('Sales Data'!C5:C24,'Sales Summary'!A28) -> 5

Sheet Dashboard
B1: Net Sales | G1: Gross Profit | K1: Target Achievement | P1: Transaction
B2: =SUM('Sales Data'!N2:N21) -> 22985.5 | G2: =SUM('Sales Data'!P2:P21) -> 9659.5 | K2: =COUNTIF('Sales Data'!R2:R21,"Target Met")/COUNTA('Sales Data'!A2:A21) -> 0.65 | P2: =COUNTA('Sales Data'!A2:A21) -> 20
B36: Product Category | C36: Net Sales | E36: Cashier | F36: Gross Profit | H36: Target Status | I36: Transaction
B37: Beverage | C37: =SUMIF('Sales Data'!D2:D21,Dashboard!B37,'Sales Data'!N2:N21) -> 7854.5 | E37: Angela | F37: =SUMIF('Sales Data'!C2:C21,Dashboard!E37,'Sales Data'!P2:P21) -> 2541.5 | H37: Target Met | I37: =COUNTIF('Sales Data'!R2:R21,"Target Met") -> 13
B38: Meal | C38: =SUMIF('Sales Data'!D3:D22,Dashboard!B38,'Sales Data'!N3:N22) -> 7461 | E38: Brian | F38: =SUMIF('Sales Data'!C3:C22,Dashboard!E38,'Sales Data'!P3:P22) -> 2442.5 | H38: Below Target | I38: =COUNTIF('Sales Data'!R3:R22,"Below Target") -> 7
B39: Snack | C39: =SUMIF('Sales Data'!D4:D23,Dashboard!B39,'Sales Data'!N4:N23) -> 3650.5 | E39: Carla | F39: =SUMIF('Sales Data'!C4:C23,Dashboard!E39,'Sales Data'!P4:P23) -> 2187.5
B40: Dessert | C40: =SUMIF('Sales Data'!D5:D24,Dashboard!B40,'Sales Data'!N5:N24) -> 4019.5 | E40: Daniel | F40: =SUMIF('Sales Data'!C5:C24,Dashboard!E40,'Sales Data'!P5:P24) -> 2488
